italica/__init__.py
italica/core.py
italica/formatters.py
italica-1.0.0.dist-info/licenses/LICENSE
italica-1.0.0.dist-info/METADATA
italica-1.0.0.dist-info/WHEEL
italica-1.0.0.dist-info/entry_points.txt
italica-1.0.0.dist-info/top_level.txt
italica-1.0.0.dist-info/RECORD
