Metadata-Version: 2.4
Name: italica
Version: 1.0.0
Summary: A simple library for adding markdown-style formatting to print and input functions
Home-page: https://github.com/7vntii/italica
Author: 7vntii
Author-email: 7vntii <jj9dptr57@mozmail.com>
Maintainer-email: 7vntii <jj9dptr57@mozmail.com>
License: MIT
Project-URL: Homepage, https://github.com/7vntii/italica
Project-URL: Documentation, https://github.com/7vntii/italica#readme
Project-URL: Repository, https://github.com/7vntii/italica
Project-URL: Bug Reports, https://github.com/7vntii/italica/issues
Project-URL: Source Code, https://github.com/7vntii/italica
Keywords: markdown,formatting,print,input,italic,bold,terminal,console
Classifier: Development Status :: 5 - Production/Stable
Classifier: Intended Audience :: Developers
Classifier: License :: OSI Approved :: MIT License
Classifier: Operating System :: OS Independent
Classifier: Programming Language :: Python :: 3
Classifier: Programming Language :: Python :: 3.7
Classifier: Programming Language :: Python :: 3.8
Classifier: Programming Language :: Python :: 3.9
Classifier: Programming Language :: Python :: 3.10
Classifier: Programming Language :: Python :: 3.11
Classifier: Programming Language :: Python :: 3.12
Classifier: Topic :: Software Development :: Libraries :: Python Modules
Classifier: Topic :: Text Processing :: Markup
Requires-Python: >=3.7
License-File: LICENSE
Provides-Extra: dev
Requires-Dist: pytest>=6.0; extra == "dev"
Requires-Dist: pytest-cov>=2.0; extra == "dev"
Requires-Dist: black>=21.0; extra == "dev"
Requires-Dist: flake8>=3.8; extra == "dev"
Requires-Dist: mypy>=0.800; extra == "dev"
Dynamic: author
Dynamic: home-page
Dynamic: license-file
Dynamic: requires-python
